CS501_Assignment_10_Moises_Villegas/__init__.py
CS501_Assignment_10_Moises_Villegas/tweet_analysis.py
CS501_Assignment_10_Moises_Villegas-0.0.1.dist-info/METADATA
CS501_Assignment_10_Moises_Villegas-0.0.1.dist-info/WHEEL
CS501_Assignment_10_Moises_Villegas-0.0.1.dist-info/top_level.txt
CS501_Assignment_10_Moises_Villegas-0.0.1.dist-info/RECORD
