Metadata-Version: 2.1
Name: CS501-Assignment-10-Moises-Villegas
Version: 0.0.1
Summary: Assignment 10
Author: Moises Villegas
Author-email: <mvilleg1@g.emporia.edu>
Keywords: python,Assignment 10
Classifier: Programming Language :: Python :: 3
